{
  "name": "13::Page Delete",
  "url": "http://localhost:8081/",
  "setup_function": "created_page_page",
  "actions": [
    {
      "action": "Click \"Delete\" link in the page actions",
      "expectedResult": "Delete confirmation dialog appears"
    },
    {
      "action": "Click \"Confirm\" button in the confirmation dialog",
      "expectedResult": "Page deletion is confirmed"
    },
    {
      "action": "Verify user is redirected away from deleted page",
      "expectedResult": "User is no longer on the deleted page"
    },
    {
      "action": "Verify page no longer appears in book navigation",
      "expectedResult": "Page is removed from book structure"
    }
  ]
}